battlepy/__init__.py
battlepy/armor.py
battlepy/battle.py
battlepy/character.py
battlepy/config.py
battlepy/functions.py
battlepy/quality.py
battlepy/stats.py
battlepy/weapon.py
battlepy/config/acessories.csv
battlepy/config/armor.csv
battlepy/config/class.csv
battlepy/config/config.json
battlepy/config/header.csv
battlepy/config/primary_weapons.csv
battlepy/config/quality.csv
battlepy/config/stats.csv
battlepy/config/weapon.csv
battlepy-1.0.1b0.dist-info/METADATA
battlepy-1.0.1b0.dist-info/WHEEL
battlepy-1.0.1b0.dist-info/licenses/LICENSE
battlepy-1.0.1b0.dist-info/RECORD
