Metadata-Version: 2.1
Name: battlepy
Version: 1.0.1b0
Summary: Battle log generator
Project-URL: Homepage, https://github.com/FabioPolini/battlepy
Project-URL: Bug Tracker, https://github.com/FabioPolini/battlepy/issues
Author-email: Fabio Polini <60330659+FabioPolini@users.noreply.github.com>
License-File: LICENSE
Classifier: License :: OSI Approved :: MIT License
Classifier: Operating System :: OS Independent
Classifier: Programming Language :: Python :: 3
Requires-Python: >=3.7
